tag_a_day/__init__.py
tag_a_day/cache.py
tag_a_day/cli.py
tag_a_day/config.py
tag_a_day/log.py
tag_a_day/actions/__init__.py
tag_a_day/actions/reconcile.py
tag_a_day/prompt/__init__.py
tag_a_day/prompt/validators.py
tag_a_day/services/__init__.py
tag_a_day/services/ec2.py
tag_a_day/services/emr.py
tag_a_day/services/rds.py
tag_a_day/services/s3.py
tag_a_day/services/service.py
aws_tag_a_day-0.1.10.dist-info/LICENSE
aws_tag_a_day-0.1.10.dist-info/METADATA
aws_tag_a_day-0.1.10.dist-info/WHEEL
aws_tag_a_day-0.1.10.dist-info/entry_points.txt
aws_tag_a_day-0.1.10.dist-info/top_level.txt
aws_tag_a_day-0.1.10.dist-info/RECORD
