Metadata-Version: 2.1
Name: aws-tag-a-day
Version: 0.1.10
Summary: A tool for simplifying swarming of fixing AWS tags
Home-page: https://github.com/bliseng/aws-tag-a-day
Author: Drew J. Sonne
Author-email: drew.sonne@gmail.com
License: Apache2
Platform: UNKNOWN
Requires-Dist: tabulate
Requires-Dist: hconf
Requires-Dist: pyyaml
Requires-Dist: boto3
Requires-Dist: setuptools (>=13)
